{"england_premiership": {"QPR": 19, "Crystal Palace": 7, "Watford": 26, "Bournemouth": 2, "Swansea": 24, "Norwich": 18, "West Ham": 28, "Southampton": 21, "Stoke": 22, "Chelsea": 6, "Cardiff": 5, "Huddersfield": 10, "Wigan": 29, "Fulham": 9, "Reading": 20, "Tottenham": 25, "Sunderland": 23, "Leicester": 12, "Brighton": 3, "Burnley": 4, "Man City": 14, "Aston Villa": 1, "Hull": 11, "Newcastle": 17, "Everton": 8, "Man United": 15, "Middlesbrough": 16, "Liverpool": 13, "Arsenal": 0, "West Brom": 27}}