{"netherlands_eredivisie": {"Excelsior": 12, "Genk": 15, "Go Ahead Eagles": 17, "Ajax": 1, "Gent": 16, "Zwolle": 43, "Breda": 4, "Charleroi": 7, "Dordrecht": 10, "Kortrijk": 22, "Heerenveen": 20, "Heracles": 21, "VVV Venlo": 37, "PSV Eindhoven": 29, "PSV": 28, "Cercle Brugge": 6, "Roda": 30, "Anderlecht": 2, "Willem II": 42, "Vitesse": 38, "Utrecht": 36, "Antwerp": 3, "Mouscron": 24, "Groningen": 19, "Waregem": 41, "Club Brugge": 8, "Graafschap": 18, "AZ Alkmaar": 0, "Standard": 34, "St Truiden": 33, "Feyenoord": 14, "Eupen": 11, "Waasland-Beveren": 40, "FC Emmen": 13, "Den Haag": 9, "Lokeren": 23, "Cambuur": 5, "NAC Breda": 25, "Oostende": 27, "Sittard": 31, "Sparta Rotterdam": 32, "Twente": 35, "Waalwijk": 39, "Nijmegen": 26}}